<annotation>
	<folder>D:\AI\SVR-dataset\2022-02\2. public\dataset\Sander lucioperca</folder>
	<filename>0d176727-4590-40c0-b427-5ceced4fed71-270mm.jpg</filename>
	<path>D:\AI\SVR-dataset\2022-02\2. public\dataset\Sander lucioperca\0d176727-4590-40c0-b427-5ceced4fed71-270mm.jpg</path>
	<source>
		<database>Unknown</database>
	</source>
	<size>
		<width>441</width>
		<height>214</height>
		<depth>3</depth>
	</size>
	<segmented>0</segmented>
    <object>
            <name>Sander lucioperca</name>
            <pose>Unspecified</pose>
            <truncated>0</truncated>
            <difficult>0</difficult>
            <bndbox>
                <xmin>20</xmin>
                <ymin>20</ymin>
                <xmax>421</xmax>
                <ymax>194</ymax>
            </bndbox>
        </object>
    </annotation>