<annotation>
	<folder>D:\AI\SVR-dataset\2022-02\2. public\dataset\Sander lucioperca</folder>
	<filename>7a5fa000-f93f-4071-a4d4-02a27b4d3eed-0mm.jpg</filename>
	<path>D:\AI\SVR-dataset\2022-02\2. public\dataset\Sander lucioperca\7a5fa000-f93f-4071-a4d4-02a27b4d3eed-0mm.jpg</path>
	<source>
		<database>Unknown</database>
	</source>
	<size>
		<width>251</width>
		<height>833</height>
		<depth>3</depth>
	</size>
	<segmented>0</segmented>
    <object>
            <name>Sander lucioperca</name>
            <pose>Unspecified</pose>
            <truncated>0</truncated>
            <difficult>0</difficult>
            <bndbox>
                <xmin>20</xmin>
                <ymin>20</ymin>
                <xmax>231</xmax>
                <ymax>813</ymax>
            </bndbox>
        </object>
    </annotation>