<annotation>
	<folder>D:\AI\SVR-dataset\2022-02\2. public\dataset\Sander lucioperca</folder>
	<filename>c91feb61-87c2-46ef-9e9b-79fa94270e5b-0mm.jpg</filename>
	<path>D:\AI\SVR-dataset\2022-02\2. public\dataset\Sander lucioperca\c91feb61-87c2-46ef-9e9b-79fa94270e5b-0mm.jpg</path>
	<source>
		<database>Unknown</database>
	</source>
	<size>
		<width>659</width>
		<height>245</height>
		<depth>3</depth>
	</size>
	<segmented>0</segmented>
    <object>
            <name>Sander lucioperca</name>
            <pose>Unspecified</pose>
            <truncated>0</truncated>
            <difficult>0</difficult>
            <bndbox>
                <xmin>20</xmin>
                <ymin>20</ymin>
                <xmax>639</xmax>
                <ymax>225</ymax>
            </bndbox>
        </object>
    </annotation>