<annotation>
	<folder>D:\AI\SVR-dataset\2022-02\2. public\dataset\Barbus barbus</folder>
	<filename>274321cf-6f22-4a2a-a0a3-6d0383f5c89f-630mm.jpg</filename>
	<path>D:\AI\SVR-dataset\2022-02\2. public\dataset\Barbus barbus\274321cf-6f22-4a2a-a0a3-6d0383f5c89f-630mm.jpg</path>
	<source>
		<database>Unknown</database>
	</source>
	<size>
		<width>800</width>
		<height>340</height>
		<depth>3</depth>
	</size>
	<segmented>0</segmented>
    <object>
            <name>Barbus barbus</name>
            <pose>Unspecified</pose>
            <truncated>0</truncated>
            <difficult>0</difficult>
            <bndbox>
                <xmin>17</xmin>
                <ymin>20</ymin>
                <xmax>780</xmax>
                <ymax>320</ymax>
            </bndbox>
        </object>
    </annotation>