<annotation>
	<folder>D:\AI\SVR-dataset\2022-02\2. public\dataset\Barbus barbus</folder>
	<filename>3c8f1847-f28e-4625-943a-a2cd51dab268-500mm.jpg</filename>
	<path>D:\AI\SVR-dataset\2022-02\2. public\dataset\Barbus barbus\3c8f1847-f28e-4625-943a-a2cd51dab268-500mm.jpg</path>
	<source>
		<database>Unknown</database>
	</source>
	<size>
		<width>761</width>
		<height>238</height>
		<depth>3</depth>
	</size>
	<segmented>0</segmented>
    <object>
            <name>Barbus barbus</name>
            <pose>Unspecified</pose>
            <truncated>0</truncated>
            <difficult>0</difficult>
            <bndbox>
                <xmin>20</xmin>
                <ymin>20</ymin>
                <xmax>741</xmax>
                <ymax>218</ymax>
            </bndbox>
        </object>
    </annotation>