<annotation>
	<folder>D:\AI\SVR-dataset\2022-02\2. public\dataset\Barbus barbus</folder>
	<filename>b1cb36b6-01d2-42a9-a093-2909b2dec60f-690mm.jpg</filename>
	<path>D:\AI\SVR-dataset\2022-02\2. public\dataset\Barbus barbus\b1cb36b6-01d2-42a9-a093-2909b2dec60f-690mm.jpg</path>
	<source>
		<database>Unknown</database>
	</source>
	<size>
		<width>787</width>
		<height>265</height>
		<depth>3</depth>
	</size>
	<segmented>0</segmented>
    <object>
            <name>Barbus barbus</name>
            <pose>Unspecified</pose>
            <truncated>0</truncated>
            <difficult>0</difficult>
            <bndbox>
                <xmin>1</xmin>
                <ymin>20</ymin>
                <xmax>767</xmax>
                <ymax>245</ymax>
            </bndbox>
        </object>
    </annotation>