<annotation>
	<folder>D:\AI\SVR-dataset\2022-02\2. public\dataset\Rutilus rutilus</folder>
	<filename>2b239257-95c8-42aa-93dc-ed99354df81a-0mm.jpg</filename>
	<path>D:\AI\SVR-dataset\2022-02\2. public\dataset\Rutilus rutilus\2b239257-95c8-42aa-93dc-ed99354df81a-0mm.jpg</path>
	<source>
		<database>Unknown</database>
	</source>
	<size>
		<width>692</width>
		<height>277</height>
		<depth>3</depth>
	</size>
	<segmented>0</segmented>
    <object>
            <name>Rutilus rutilus</name>
            <pose>Unspecified</pose>
            <truncated>0</truncated>
            <difficult>0</difficult>
            <bndbox>
                <xmin>20</xmin>
                <ymin>20</ymin>
                <xmax>672</xmax>
                <ymax>257</ymax>
            </bndbox>
        </object>
    </annotation>