<annotation>
	<folder>D:\AI\SVR-dataset\2022-02\2. public\dataset\Rutilus rutilus</folder>
	<filename>531080e3-46fd-4876-a7d1-229b2d16a3ef-150mm.jpg</filename>
	<path>D:\AI\SVR-dataset\2022-02\2. public\dataset\Rutilus rutilus\531080e3-46fd-4876-a7d1-229b2d16a3ef-150mm.jpg</path>
	<source>
		<database>Unknown</database>
	</source>
	<size>
		<width>626</width>
		<height>212</height>
		<depth>3</depth>
	</size>
	<segmented>0</segmented>
    <object>
            <name>Rutilus rutilus</name>
            <pose>Unspecified</pose>
            <truncated>0</truncated>
            <difficult>0</difficult>
            <bndbox>
                <xmin>20</xmin>
                <ymin>20</ymin>
                <xmax>606</xmax>
                <ymax>192</ymax>
            </bndbox>
        </object>
    </annotation>