<annotation>
	<folder>D:\AI\SVR-dataset\2022-02\2. public\dataset\Rutilus rutilus</folder>
	<filename>7fc97254-fb43-4133-99c4-1a81e296e8e0-220mm.jpg</filename>
	<path>D:\AI\SVR-dataset\2022-02\2. public\dataset\Rutilus rutilus\7fc97254-fb43-4133-99c4-1a81e296e8e0-220mm.jpg</path>
	<source>
		<database>Unknown</database>
	</source>
	<size>
		<width>231</width>
		<height>739</height>
		<depth>3</depth>
	</size>
	<segmented>0</segmented>
    <object>
            <name>Rutilus rutilus</name>
            <pose>Unspecified</pose>
            <truncated>0</truncated>
            <difficult>0</difficult>
            <bndbox>
                <xmin>20</xmin>
                <ymin>20</ymin>
                <xmax>211</xmax>
                <ymax>726</ymax>
            </bndbox>
        </object>
    </annotation>