<annotation>
	<folder>D:\AI\SVR-dataset\2022-02\2. public\dataset\Leuciscus idus</folder>
	<filename>110430-530mm.jpg</filename>
	<path>D:\AI\SVR-dataset\2022-02\2. public\dataset\Leuciscus idus\110430-530mm.jpg</path>
	<source>
		<database>Unknown</database>
	</source>
	<size>
		<width>747</width>
		<height>270</height>
		<depth>3</depth>
	</size>
	<segmented>0</segmented>
    <object>
            <name>Leuciscus idus</name>
            <pose>Unspecified</pose>
            <truncated>0</truncated>
            <difficult>0</difficult>
            <bndbox>
                <xmin>20</xmin>
                <ymin>20</ymin>
                <xmax>727</xmax>
                <ymax>250</ymax>
            </bndbox>
        </object>
    </annotation>