<annotation>
	<folder>D:\AI\SVR-dataset\2022-02\2. public\dataset\Lepomis gibbosus</folder>
	<filename>97bb11e4-f18c-453a-8a5b-fbf709236304-120mm.jpg</filename>
	<path>D:\AI\SVR-dataset\2022-02\2. public\dataset\Lepomis gibbosus\97bb11e4-f18c-453a-8a5b-fbf709236304-120mm.jpg</path>
	<source>
		<database>Unknown</database>
	</source>
	<size>
		<width>626</width>
		<height>301</height>
		<depth>3</depth>
	</size>
	<segmented>0</segmented>
    <object>
            <name>Lepomis gibbosus</name>
            <pose>Unspecified</pose>
            <truncated>0</truncated>
            <difficult>0</difficult>
            <bndbox>
                <xmin>20</xmin>
                <ymin>20</ymin>
                <xmax>606</xmax>
                <ymax>281</ymax>
            </bndbox>
        </object>
    </annotation>