<annotation>
	<folder>D:\AI\SVR-dataset\2022-02\2. public\dataset\Aspius aspius</folder>
	<filename>5c371184-5a06-409c-ac7e-2c6626ee4ed9-750mm.jpg</filename>
	<path>D:\AI\SVR-dataset\2022-02\2. public\dataset\Aspius aspius\5c371184-5a06-409c-ac7e-2c6626ee4ed9-750mm.jpg</path>
	<source>
		<database>Unknown</database>
	</source>
	<size>
		<width>641</width>
		<height>347</height>
		<depth>3</depth>
	</size>
	<segmented>0</segmented>
    <object>
            <name>Aspius aspius</name>
            <pose>Unspecified</pose>
            <truncated>0</truncated>
            <difficult>0</difficult>
            <bndbox>
                <xmin>20</xmin>
                <ymin>20</ymin>
                <xmax>621</xmax>
                <ymax>327</ymax>
            </bndbox>
        </object>
    </annotation>