<annotation>
	<folder>D:\AI\SVR-dataset\2022-02\2. public\dataset\Aspius aspius</folder>
	<filename>968440e5-c0c8-44ca-ab10-a19453ecf1c0-580mm.jpg</filename>
	<path>D:\AI\SVR-dataset\2022-02\2. public\dataset\Aspius aspius\968440e5-c0c8-44ca-ab10-a19453ecf1c0-580mm.jpg</path>
	<source>
		<database>Unknown</database>
	</source>
	<size>
		<width>631</width>
		<height>256</height>
		<depth>3</depth>
	</size>
	<segmented>0</segmented>
    <object>
            <name>Aspius aspius</name>
            <pose>Unspecified</pose>
            <truncated>0</truncated>
            <difficult>0</difficult>
            <bndbox>
                <xmin>20</xmin>
                <ymin>20</ymin>
                <xmax>611</xmax>
                <ymax>236</ymax>
            </bndbox>
        </object>
    </annotation>