<annotation>
	<folder>D:\AI\SVR-dataset\2022-02\2. public\dataset\Aspius aspius</folder>
	<filename>b2b2a86e-cee0-45e2-bb9e-0e67cbe40902-680mm.jpg</filename>
	<path>D:\AI\SVR-dataset\2022-02\2. public\dataset\Aspius aspius\b2b2a86e-cee0-45e2-bb9e-0e67cbe40902-680mm.jpg</path>
	<source>
		<database>Unknown</database>
	</source>
	<size>
		<width>237</width>
		<height>812</height>
		<depth>3</depth>
	</size>
	<segmented>0</segmented>
    <object>
            <name>Aspius aspius</name>
            <pose>Unspecified</pose>
            <truncated>0</truncated>
            <difficult>0</difficult>
            <bndbox>
                <xmin>20</xmin>
                <ymin>20</ymin>
                <xmax>217</xmax>
                <ymax>805</ymax>
            </bndbox>
        </object>
    </annotation>