<annotation>
	<folder>D:\AI\SVR-dataset\2022-02\2. public\dataset\Esox lucius</folder>
	<filename>d45bd667-4989-4aab-bc01-e84e50e50167-980mm.jpg</filename>
	<path>D:\AI\SVR-dataset\2022-02\2. public\dataset\Esox lucius\d45bd667-4989-4aab-bc01-e84e50e50167-980mm.jpg</path>
	<source>
		<database>Unknown</database>
	</source>
	<size>
		<width>765</width>
		<height>295</height>
		<depth>3</depth>
	</size>
	<segmented>0</segmented>
    <object>
            <name>Esox lucius</name>
            <pose>Unspecified</pose>
            <truncated>0</truncated>
            <difficult>0</difficult>
            <bndbox>
                <xmin>20</xmin>
                <ymin>20</ymin>
                <xmax>745</xmax>
                <ymax>275</ymax>
            </bndbox>
        </object>
    </annotation>