<annotation>
	<folder>D:\AI\SVR-dataset\2022-02\2. public\dataset\Cyprinus carpio</folder>
	<filename>72e6ff2d-9230-4d36-ace6-33fa945917b7-0mm.jpg</filename>
	<path>D:\AI\SVR-dataset\2022-02\2. public\dataset\Cyprinus carpio\72e6ff2d-9230-4d36-ace6-33fa945917b7-0mm.jpg</path>
	<source>
		<database>Unknown</database>
	</source>
	<size>
		<width>524</width>
		<height>311</height>
		<depth>3</depth>
	</size>
	<segmented>0</segmented>
    <object>
            <name>Cyprinus carpio</name>
            <pose>Unspecified</pose>
            <truncated>0</truncated>
            <difficult>0</difficult>
            <bndbox>
                <xmin>20</xmin>
                <ymin>20</ymin>
                <xmax>504</xmax>
                <ymax>291</ymax>
            </bndbox>
        </object>
    </annotation>