<annotation>
	<folder>D:\AI\SVR-dataset\2022-02\2. public\dataset\Anguilla anguilla</folder>
	<filename>d9f322e0-1287-468c-91b1-0543d3935c0b-570mm.jpg</filename>
	<path>D:\AI\SVR-dataset\2022-02\2. public\dataset\Anguilla anguilla\d9f322e0-1287-468c-91b1-0543d3935c0b-570mm.jpg</path>
	<source>
		<database>Unknown</database>
	</source>
	<size>
		<width>794</width>
		<height>184</height>
		<depth>3</depth>
	</size>
	<segmented>0</segmented>
    <object>
            <name>Anguilla anguilla</name>
            <pose>Unspecified</pose>
            <truncated>0</truncated>
            <difficult>0</difficult>
            <bndbox>
                <xmin>7</xmin>
                <ymin>20</ymin>
                <xmax>774</xmax>
                <ymax>164</ymax>
            </bndbox>
        </object>
    </annotation>