<annotation>
	<folder>D:\AI\SVR-dataset\2022-02\2. public\dataset\Ctenopharyngodon idella</folder>
	<filename>df24d3eb-00cf-4795-916b-f26e7b27c382-810mm.jpg</filename>
	<path>D:\AI\SVR-dataset\2022-02\2. public\dataset\Ctenopharyngodon idella\df24d3eb-00cf-4795-916b-f26e7b27c382-810mm.jpg</path>
	<source>
		<database>Unknown</database>
	</source>
	<size>
		<width>492</width>
		<height>285</height>
		<depth>3</depth>
	</size>
	<segmented>0</segmented>
    <object>
            <name>Ctenopharyngodon idella</name>
            <pose>Unspecified</pose>
            <truncated>0</truncated>
            <difficult>0</difficult>
            <bndbox>
                <xmin>20</xmin>
                <ymin>20</ymin>
                <xmax>472</xmax>
                <ymax>265</ymax>
            </bndbox>
        </object>
    </annotation>